pybeginners/__init__.py
pybeginners/programs.py
pybeginners-1.0.1.dist-info/LICENSE
pybeginners-1.0.1.dist-info/METADATA
pybeginners-1.0.1.dist-info/WHEEL
pybeginners-1.0.1.dist-info/top_level.txt
pybeginners-1.0.1.dist-info/RECORD
