Metadata-Version: 2.1
Name: pybeginners
Version: 1.0.1
Summary: A package to use some basic numeric/math functionalities
Home-page: https://github.com/amrs-tech/pybeginners
Author: Ahamed Musthafa
Author-email: amrs.tech@gmail.com
License: UNKNOWN
Platform: UNKNOWN
Classifier: Programming Language :: Python :: 3
Classifier: License :: OSI Approved :: MIT License
Classifier: Operating System :: OS Independent
Requires-Python: >=3.4
